<?xml version="1.0" encoding="UTF-8"?>
<monster name="Brain Squid" nameDescription="a brain squid" race="undead" experience="17672" speed="430">
	<health now="18000" max="18000"/>
	<look type="1765" head="97" body="18" legs="61" feet="0" corpse="6065"/>
	<targetchange interval="5000" chance="8"/>
	<flags>
		<flag summonable="0"/>
		<flag attackable="1"/>
		<flag hostile="1"/>
		<flag illusionable="0"/>
		<flag convinceable="0"/>
		<flag pushable="0"/>
		<flag canpushitems="1"/>
		<flag canpushcreatures="1"/>
		<flag targetdistance="1"/>
		<flag staticattack="90"/>
		<flag runonhealth="0"/>
	</flags>
	<attacks>
		<attack name="melee" interval="2000" min="-100" max="-700"/>
		<attack name="energy" interval="2000" chance="15" range="7" min="-700" max="-1000">
			<attribute key="shootEffect" value="energy"/>
		</attack>
		<attack name="energy" interval="2000" chance="13" radius="3" min="-600" max="-905">
			<attribute key="areaEffect" value="energyarea"/>
		</attack>
		<attack name="holy" interval="2000" chance="13" radius="3" min="-800" max="-1005">
		<attribute key="areaEffect" value="yellowspark"/>
		</attack>		
	</attacks>
	<defenses armor="82" defense="40"/>
	<elements>
		<element icePercent="50"/>
		<element earthPercent="30"/>
		<element holyPercent="70"/>
		<element firePercent="50"/>
		<element energyPercent="90"/>
		<element deathPercent="50"/>
	</elements>
	<immunities>
		<immunity invisible="1"/>
  </immunities>
  <loot>
  <item id="6500" countmax="1" chance="3000" /> <!-- ritual point -->
  <item id="5880" countmax="2" chance="3000" /> <!-- ritual point -->
 <item id="2160" countmax="2" chance="100" /> <!-- ritual point -->
<item id="13397" countmax="2" chance="50" /> <!-- ritual point -->
<item id="8981" countmax="2" chance="20" /> <!-- ritual point -->
<item id="13393" countmax="2" chance="20" /> <!-- ritual point -->	 
<item id="2152" countmax="7" chance="10000" /> <!-- platinum  -->
<item id="2666" countmax="3" chance="30000" /> <!-- food  -->
<item id="7889" countmax="1" chance="1000" /> <!-- light pendant  -->
<item id="2147" countmax="4" chance="5000" /> <!-- small ruby  -->
<item id="13213" countmax="4" chance="5000" /> <!-- ulti mana pot  -->
<item id="7901" countmax="1" chance="1000" /> <!-- light helmet  -->
<item id="2164" countmax="1" chance="1200" /> <!-- might ring  -->
<item id="7901" countmax="1" chance="1000" /> <!-- food  -->
  </loot>
</monster>